check_in/__init__.py
check_in/__main__.py
check_in/cli.py
check_in/github_api.py
check_in/github_checks_requests.py
check_in-0.6.0.dist-info/LICENSE.rst
check_in-0.6.0.dist-info/METADATA
check_in-0.6.0.dist-info/WHEEL
check_in-0.6.0.dist-info/entry_points.txt
check_in-0.6.0.dist-info/top_level.txt
check_in-0.6.0.dist-info/RECORD
